django_asse.py
django_async_sse-1.0.0.dist-info/METADATA
django_async_sse-1.0.0.dist-info/WHEEL
django_async_sse-1.0.0.dist-info/licenses/LICENSE
django_async_sse-1.0.0.dist-info/RECORD
