Metadata-Version: 2.1
Name: django-async-sse
Version: 1.0.0
Summary: Django async Server Sent Events helpers
Home-page: https://github.com/pizzapanther/django-async-sse
Author-Email: Paul Bailey <paul@neutron.studio>
License: BSD-3Clause
Project-URL: Homepage, https://github.com/pizzapanther/django-async-sse
Requires-Python: >=3.10
